[{"id":1,"user":{"id":2,"username":"jeremey","password":"96166E27AF5A3C431FFA7247AD4E1B2D488008311887CEDC655121565721CBCE","firstName":"Jeremey","surname":"Sas","email":null,"phone":null,"birthdate":"0001-01-01T00:00:00","status":0},"products":[],"numberguests":4,"diningtable":{"id":9,"places":4,"description":"tafel 9","status":"Bezet"},"createdatetime":"2022-06-01T21:59:28.8848807+02:00","duedatetime":"2023-03-09T00:00:00","comment":"","totalcosts":0,"status":"Actief","reservecode":"1631"},{"id":2,"user":{"id":2,"username":"jeremey","password":"96166E27AF5A3C431FFA7247AD4E1B2D488008311887CEDC655121565721CBCE","firstName":"Jeremey","surname":"Sas","email":null,"phone":null,"birthdate":"0001-01-01T00:00:00","status":0},"products":[],"numberguests":2,"diningtable":{"id":1,"places":2,"description":"tafel 1","status":"Vrij"},"createdatetime":"2022-06-01T22:03:42.5866581+02:00","duedatetime":"2023-03-09T00:00:00","comment":"","totalcosts":0,"status":"Actief","reservecode":"5067"},{"id":3,"user":{"id":3,"username":"test","password":"1B4F0E9851971998E732078544C96B36C3D01CEDF7CAA332359D6F1D83567014","firstName":"Test","surname":null,"email":null,"phone":null,"birthdate":"0001-01-01T00:00:00","status":0},"products":[],"numberguests":4,"diningtable":{"id":9,"places":4,"description":"tafel 9","status":"Bezet"},"createdatetime":"2022-06-07T22:32:12.3596747+02:00","duedatetime":"2023-03-09T20:00:00","comment":"","totalcosts":0,"status":"Actief","reservecode":"3275"}]